aiogram_inline_paginations/__init__.py
aiogram_inline_paginations/paginator.py
aiogram_inline_paginations-0.1.11.dist-info/LICENSE
aiogram_inline_paginations-0.1.11.dist-info/WHEEL
aiogram_inline_paginations-0.1.11.dist-info/METADATA
aiogram_inline_paginations-0.1.11.dist-info/RECORD
