Metadata-Version: 2.1
Name: aiogram-inline-paginations
Version: 0.1.11
Summary: A simple library for aiogram that allows you to easily do pagination for any Inline keyboards.
Home-page: https://github.com/daniilshamraev/aiogram-inline-paginations
License: MIT
Author: Daniil Shamraev
Author-email: shamraev.2002@gmail.com
Requires-Python: >=3.10,<4.0
Classifier: License :: OSI Approved :: MIT License
Classifier: Programming Language :: Python :: 3
Classifier: Programming Language :: Python :: 3.10
Classifier: Programming Language :: Python :: 3.11
Requires-Dist: aiogram (>=3.0.0b6,<4.0.0)
Requires-Dist: pip (>=22.1.2,<23.0.0)
Requires-Dist: setuptools (>=65.7.0,<66.0.0)
Requires-Dist: wheel (>=0.38.4,<0.39.0)
Project-URL: Repository, https://github.com/daniilshamraev/aiogram-inline-paginations
